Workbook

Sheet Terms of loan
B1: Loan workbook
B3: Principal Amount: | D3: 20000 | E3: Monthly Payment
B4: Interest Rate: | D4: 0.12 | F4: =PMT(D4/12,D5,-D3) -> 444.88895
B5: Term in Months: | D5: 60

Sheet Detail sheet for 5-year loan
C5: Beginning | F5: Remaining
B6: Month | C6: Principal | D6: Interest | E6: Principal | F6: Principal
C7: Balance | D7: Paid | E7: Paid | F7: Amount
B9: 1 | C9: ='Terms of loan'!D3 -> 20000 | D9: =IF(+B9<='Terms of loan'!$D$5,+C9*('Terms of loan'!$D$4/12),0) -> 200 | E9: =IF(+B9<='Terms of loan'!$D$5,'Terms of loan'!$F$4-D9,0) -> 244.88895 | F9: =IF(+B9<='Terms of loan'!$D$5,+C9-E9,0) -> 19755.111
B10: 2 | C10: =F9 -> 19755.111 | D10: =IF(+B10<='Terms of loan'!$D$5,+C10*('Terms of loan'!$D$4/12),0) -> 197.55111 | E10: =IF(+B10<='Terms of loan'!$D$5,'Terms of loan'!$F$4-D10,0) -> 247.33784 | F10: =IF(+B10<='Terms of loan'!$D$5,+C10-E10,0) -> 19507.773
B11: 3 | C11: =F10 -> 19507.773 | D11: =IF(+B11<='Terms of loan'!$D$5,+C11*('Terms of loan'!$D$4/12),0) -> 195.07773 | E11: =IF(+B11<='Terms of loan'!$D$5,'Terms of loan'!$F$4-D11,0) -> 249.81122 | F11: =IF(+B11<='Terms of loan'!$D$5,+C11-E11,0) -> 19257.962
B12: 4 | C12: =F11 -> 19257.962 | D12: =IF(+B12<='Terms of loan'!$D$5,+C12*('Terms of loan'!$D$4/12),0) -> 192.57962 | E12: =IF(+B12<='Terms of loan'!$D$5,'Terms of loan'!$F$4-D12,0) -> 252.30933 | F12: =IF(+B12<='Terms of loan'!$D$5,+C12-E12,0) -> 19005.653
B13: 5 | C13: =F12 -> 19005.653 | D13: =IF(+B13<='Terms of loan'!$D$5,+C13*('Terms of loan'!$D$4/12),0) -> 190.05653 | E13: =IF(+B13<='Terms of loan'!$D$5,'Terms of loan'!$F$4-D13,0) -> 254.83243 | F13: =IF(+B13<='Terms of loan'!$D$5,+C13-E13,0) -> 18750.82
B14: 6 | C14: =F13 -> 18750.82 | D14: =IF(+B14<='Terms of loan'!$D$5,+C14*('Terms of loan'!$D$4/12),0) -> 187.5082 | E14: =IF(+B14<='Terms of loan'!$D$5,'Terms of loan'!$F$4-D14,0) -> 257.38075 | F14: =IF(+B14<='Terms of loan'!$D$5,+C14-E14,0) -> 18493.439
B15: 7 | C15: =F14 -> 18493.439 | D15: =IF(+B15<='Terms of loan'!$D$5,+C15*('Terms of loan'!$D$4/12),0) -> 184.93439 | E15: =IF(+B15<='Terms of loan'!$D$5,'Terms of loan'!$F$4-D15,0) -> 259.95456 | F15: =IF(+B15<='Terms of loan'!$D$5,+C15-E15,0) -> 18233.485
B16: 8 | C16: =F15 -> 18233.485 | D16: =IF(+B16<='Terms of loan'!$D$5,+C16*('Terms of loan'!$D$4/12),0) -> 182.33485 | E16: =IF(+B16<='Terms of loan'!$D$5,'Terms of loan'!$F$4-D16,0) -> 262.5541 | F16: =IF(+B16<='Terms of loan'!$D$5,+C16-E16,0) -> 17970.931
B17: 9 | C17: =F16 -> 17970.931 | D17: =IF(+B17<='Terms of loan'!$D$5,+C17*('Terms of loan'!$D$4/12),0) -> 179.70931 | E17: =IF(+B17<='Terms of loan'!$D$5,'Terms of loan'!$F$4-D17,0) -> 265.17965 | F17: =IF(+B17<='Terms of loan'!$D$5,+C17-E17,0) -> 17705.751
B18: 10 | C18: =F17 -> 17705.751 | D18: =IF(+B18<='Terms of loan'!$D$5,+C18*('Terms of loan'!$D$4/12),0) -> 177.05751 | E18: =IF(+B18<='Terms of loan'!$D$5,'Terms of loan'!$F$4-D18,0) -> 267.83144 | F18: =IF(+B18<='Terms of loan'!$D$5,+C18-E18,0) -> 17437.92
B19: 11 | C19: =F18 -> 17437.92 | D19: =IF(+B19<='Terms of loan'!$D$5,+C19*('Terms of loan'!$D$4/12),0) -> 174.3792 | E19: =IF(+B19<='Terms of loan'!$D$5,'Terms of loan'!$F$4-D19,0) -> 270.50976 | F19: =IF(+B19<='Terms of loan'!$D$5,+C19-E19,0) -> 17167.41
B20: 12 | C20: =F19 -> 17167.41 | D20: =IF(+B20<='Terms of loan'!$D$5,+C20*('Terms of loan'!$D$4/12),0) -> 171.6741 | E20: =IF(+B20<='Terms of loan'!$D$5,'Terms of loan'!$F$4-D20,0) -> 273.21485 | F20: =IF(+B20<='Terms of loan'!$D$5,+C20-E20,0) -> 16894.195
B21: 13 | C21: =F20 -> 16894.195 | D21: =IF(+B21<='Terms of loan'!$D$5,+C21*('Terms of loan'!$D$4/12),0) -> 168.94195 | E21: =IF(+B21<='Terms of loan'!$D$5,'Terms of loan'!$F$4-D21,0) -> 275.947 | F21: =IF(+B21<='Terms of loan'!$D$5,+C21-E21,0) -> 16618.248
... B68: 60 | C68: =F67 -> 440.48411 | D68: =IF(+B68<='Terms of loan'!$D$5,+C68*('Terms of loan'!$D$4/12),0) -> 4.4048411 | E68: =IF(+B68<='Terms of loan'!$D$5,'Terms of loan'!$F$4-D68,0) -> 440.48411 | F68: =IF(+B68<='Terms of loan'!$D$5,+C68-E68,0) -> 1.745093e-11
B70: TOTALS: | D70: =SUM(D9:D68) -> 6693.3372 | E70: =SUM(E9:E68) -> 20000

Sheet Sheet3
